IMEM.v
// IMEM
// Universidad del Valle de Guatemala
// Curso: Arquitectura de Computadores
// Autor: Samuel Tortola - 22094
// Fecha: 13/10/2025



module IMEM(
    input  wire [31:0] addr,        // Dirección de la instrucción
    output wire [31:0] instruction // Instrucción leída
);

    reg [31:0] memory [0:15]; // Memoria de 16 palabras de 32 bits

    initial begin
        memory[0] = 32'b000000_00001_00010_00011_00000_100000; // ADD $3, $1, $2
        memory[1] = 32'b001000_01000_01001_0000000000001010;   // ADDI $9, $8, 10
        memory[2] = 32'b000100_00001_00010_0000000000000100;   // BEQ $1, $2, 4
        memory[3] = 32'b100011_00001_00010_0000000000000000;   // LW $2, 0($1)
        memory[4] = 32'b101011_00001_00010_0000000000000000;   // SW $2, 0($1)
        memory[5] = 32'b000000_00010_00011_00100_00000_100010; // SUB $4, $2, $3
        memory[6] = 32'b000000_00011_00100_00101_00000_100100; // AND $5, $3, $4
        memory[7] = 32'b000000_00100_00101_00110_00000_100101; // OR $6, $4, $5
        memory[8] = 32'b000000_00101_00110_00111_00000_101010; // SLT $7, $5, $6
        memory[9] = 32'b000010_00000000000000000000001100;     // J 12
       
    end

    assign instruction = memory[addr[4:0]]; // Usa los 5 bits menos significativos

endmodule

Testbench.v
module testbench_PC;

//**********************************************************************************************

    // ================================================
    // 1. DECLARACIÓN DE SEÑALES
    // ================================================
    // Señales para conectar al DUT (Design Under Test)

    reg clk;
    reg reset;
    reg [31:0] next_pc;
    wire [31:0] current_pc;


    integer start, finish;

     // ================================================
    // 2. INSTANCIACIÓN DEL DISEÑO BAJO PRUEBA (DUT)
    // ================================================

     PC dut (
        .clk(clk),
        .reset(reset),
        .next_pc(next_pc),
        .current_pc(current_pc)
    );


     // ================================================
    // 3. GENERACIÓN DE ESTÍMULOS Y MONITOREO
    // ================================================


    // Generación de reloj
    initial begin
        clk = 0;
        forever #5 clk = ~clk; // Periodo de 10 unidades de tiempo
    end

   // Estímulos y monitoreo
    initial begin
        reset = 1;
        next_pc = 32'h00000000;
        #10; // Espera algunos ciclos de reloj

        reset = 0; // Desactiva reset

        // Prueba: cambia next_pc cada ciclo
        repeat (8) begin
            @(posedge clk);
            $display("Time=%0t | reset=%b | next_pc=%h | current_pc=%h", $time, reset, next_pc, current_pc);
            next_pc = next_pc + 32'h4; // Incrementa en 4 
        end

        $finish;
    end

    initial begin
        $dumpfile("pc_tb.vcd");
        $dumpvars(0, testbench);
    end

endmodule



//**********************************************************************************************

module testbench_imem;

    reg [31:0] addr;
    wire [31:0] instruction;

    // Instancia del módulo IMEM
    IMEM dut (
        .addr(addr),
        .instruction(instruction)
    );

    integer i;



    initial begin
        $display("Addr   | Instruction         | Opcode | rs | rt | rd | shamt | funct | immediate");
     
        for (i = 0; i < 10; i = i + 1) begin
            addr = i;
            #1; // Espera a que instruction se actualice

            // Extrae campos para tipo R
            $display("%2d     | %h | %2b     | %2d | %2d | %2d | %2d    | %2d    | %h",
                addr,
                instruction,
                instruction[31:26], // opcode
                instruction[25:21], // rs
                instruction[20:16], // rt
                instruction[15:11], // rd
                instruction[10:6],  // shamt
                instruction[5:0],   // funct
                instruction[15:0]   // immediate
            );
        end
        $finish;
    end

    initial begin
        $dumpfile("imem_tb.vcd");
        $dumpvars(0, testbench_imem);
    end

endmodule


//**********************************************************************************************

module testbench_PC_IMEM;

    reg clk;
    reg reset;
    reg [31:0] next_pc;
    wire [31:0] current_pc;
    wire [31:0] instruction;

    // Instancia del PC
    PC pc_inst (
        .clk(clk),
        .reset(reset),
        .next_pc(next_pc),
        .current_pc(current_pc)
    );

    // Instancia de IMEM
    IMEM imem_inst (
        .addr(current_pc),
        .instruction(instruction)
    );

    integer i;

    // Generación de reloj
    initial begin
        clk = 0;
        forever #5 clk = ~clk;
    end

    initial begin
        reset = 1;
        next_pc = 0;
        #12;
        reset = 0;

        // Avanza el PC automáticamente y muestra instrucción y campos
        for (i = 0; i < 10; i = i + 1) begin
            @(posedge clk);
            next_pc = current_pc + 1; // Avanza de 4 en 4 (tamaño típico de instrucción MIPS)

            $display("PC=%0d, Instr=%b", current_pc, instruction);
            $display("opcode=%b rs=%b rt=%b rd=%b shamt=%b funct=%b immediate=%b",
                instruction[31:26], // opcode
                instruction[25:21], // rs
                instruction[20:16], // rt
                instruction[15:11], // rd
                instruction[10:6],  // shamt
                instruction[5:0],   // funct
                instruction[15:0]   // immediate
            );
            $display("");
        end

        $finish;
    end

    initial begin
        $dumpfile("pc_imem_tb.vcd");
        $dumpvars(0, testbench_PC_IMEM);
    end

endmodule


//**********************************************************************************************

imem_tb.vcd
$date
	Mon Oct 13 15:19:20 2025
$end
$version
	Icarus Verilog
$end
$timescale
	1s
$end
$scope module testbench_imem $end
$var wire 32 ! instruction [31:0] $end
$var reg 32 " addr [31:0] $end
$var integer 32 # i [31:0] $end
$scope module dut $end
$var wire 32 $ addr [31:0] $end
$var wire 32 % instruction [31:0] $end
$upscope $end
$upscope $end
$enddefinitions $end
$comment Show the parameter values. $end
$dumpall
$end
#0
$dumpvars
b1000100001100000100000 %
b0 $
b0 #
b0 "
b1000100001100000100000 !
$end
#1
b100001000010010000000000001010 !
b100001000010010000000000001010 %
b1 "
b1 $
b1 #
#2
b10000001000100000000000000100 !
b10000001000100000000000000100 %
b10 "
b10 $
b10 #
#3
b10001100001000100000000000000000 !
b10001100001000100000000000000000 %
b11 "
b11 $
b11 #
#4
b10101100001000100000000000000000 !
b10101100001000100000000000000000 %
b100 "
b100 $
b100 #
#5
b10000110010000000100010 !
b10000110010000000100010 %
b101 "
b101 $
b101 #
#6
b11001000010100000100100 !
b11001000010100000100100 %
b110 "
b110 $
b110 #
#7
b100001010011000000100101 !
b100001010011000000100101 %
b111 "
b111 $
b111 #
#8
b101001100011100000101010 !
b101001100011100000101010 %
b1000 "
b1000 $
b1000 #
#9
b1000000000000000000000001100 !
b1000000000000000000000001100 %
b1001 "
b1001 $
b1001 #
#10
b1010 #
