IMEM.v
// IMEM
// Universidad del Valle de Guatemala
// Curso: Arquitectura de Computadores
// Autor: Samuel Tortola - 22094, Alan Gomez - 22115
// Fecha: 13/10/2025

//El Instruction Memory (IMEM) es una memoria que almacena las instrucciones del programa que la CPU debe ejecutar.
//Cada instrucción es una palabra de 32 bits, y la IMEM permite acceder a estas instrucciones utilizando una dirección específica.
// La CPU utiliza la dirección proporcionada por el Program Counter (PC) para leer la instrucción correspondiente desde la IMEM.



module IMEM( 
    input  wire [31:0] addr,        // Dirección de la instrucción
    output wire [31:0] instruction // Instrucción leída
);

    reg [31:0] memory [0:15]; // Memoria de 16 palabras de 32 bits

    initial begin
        memory[0] = 32'b000000_00001_00010_00011_00000_100000; // ADD $3, $1, $2
        memory[1] = 32'b001000_01000_01001_0000000000001010; // ADDI $9, $8, 10 
        memory[2] = 32'b000000_00001_00010_00011_00000_100000; // ADD $3, $1, $2
        memory[3] = 32'b000000_00011_00100_00101_00000_100010; // SUB $5, $3, $4
        memory[4] = 32'b000000_00101_00110_00111_00000_100100; // AND $7, $5, $6
        memory[5] = 32'b000000_00111_01000_01001_00000_100101; // OR $9, $7, $8
        memory[6] = 32'b000000_01001_01010_01011_00000_101010; // SLT $11, $9, $10
        memory[7] = 32'b000000_01011_01100_01101_00000_000000; // SLL $13, $12, $11 (shamt=0)
        memory[8] = 32'b000000_01101_01110_01111_00000_000010; // SRL $15, $14, $13 (shamt=0)
        memory[9] = 32'b000000_01111_10000_10001_00000_100000; // ADD $17, $15, $16
        memory[10] = 32'b000000_10001_10010_10011_00000_100010; // SUB $19, $17, $18
        memory[11] = 32'b000000_10011_10100_10101_00000_100100; // AND $21, $19, $20
       
    end

    assign instruction = memory[addr[4:0]]; // Usa los 5 bits menos significativos

endmodule

Testbench.v
module testbench_PC;

//**********************************************************************************************

    // ================================================
    // 1. DECLARACIÓN DE SEÑALES
    // ================================================
    // Señales para conectar al DUT (Design Under Test)

    reg clk;
    reg reset;
    reg [31:0] next_pc;
    wire [31:0] current_pc;


    integer start, finish;

     // ================================================
    // 2. INSTANCIACIÓN DEL DISEÑO BAJO PRUEBA (DUT)
    // ================================================

     PC dut (
        .clk(clk),
        .reset(reset),
        .next_pc(next_pc),
        .current_pc(current_pc)
    );


     // ================================================
    // 3. GENERACIÓN DE ESTÍMULOS Y MONITOREO
    // ================================================


    // Generación de reloj
    initial begin
        clk = 0;
        forever #5 clk = ~clk; // Periodo de 10 unidades de tiempo
    end

   // Estímulos y monitoreo
    initial begin
        reset = 1;
        next_pc = 32'h00000000;
        #10; // Espera algunos ciclos de reloj

        reset = 0; // Desactiva reset

        // Prueba: cambia next_pc cada ciclo
        repeat (8) begin
            @(posedge clk);
            $display("Time=%0t | reset=%b | next_pc=%h | current_pc=%h", $time, reset, next_pc, current_pc);
            next_pc = next_pc + 32'h4; // Incrementa en 4 
        end

        $finish;
    end

    initial begin
        $dumpfile("pc_tb.vcd");
        $dumpvars(0, testbench);
    end

endmodule



//**********************************************************************************************

module testbench_imem;

    reg [31:0] addr;
    wire [31:0] instruction;

    // Instancia del módulo IMEM
    IMEM dut (
        .addr(addr),
        .instruction(instruction)
    );

    integer i;



    initial begin
        $display("Addr   | Instruction         | Opcode | rs | rt | rd | shamt | funct | immediate");
     
        for (i = 0; i < 12; i = i + 1) begin
            addr = i;
            #1; // Espera a que instruction se actualice

            // Extrae campos para tipo R
            $display("%2d     | %h | %2b     | %2d | %2d | %2d | %2d    | %2d    | %h",
                addr,
                instruction,
                instruction[31:26], // opcode
                instruction[25:21], // rs
                instruction[20:16], // rt
                instruction[15:11], // rd
                instruction[10:6],  // shamt
                instruction[5:0],   // funct
                instruction[15:0]   // immediate
            );
        end
        $finish;
    end

    initial begin
        $dumpfile("imem_tb.vcd");
        $dumpvars(0, testbench_imem);
    end

endmodule


//**********************************************************************************************

module testbench_PC_IMEM;

    reg clk;
    reg reset;
    reg [31:0] next_pc;
    wire [31:0] current_pc;
    wire [31:0] instruction;

    // Instancia del PC
    PC pc_inst (
        .clk(clk),
        .reset(reset),
        .next_pc(next_pc),
        .current_pc(current_pc)
    );

    // Instancia de IMEM
    IMEM imem_inst (
        .addr(current_pc),
        .instruction(instruction)
    );

    integer i;

    // Generación de reloj
    initial begin
        clk = 0;
        forever #5 clk = ~clk;
    end

    initial begin
        reset = 1;
        next_pc = 0;
        #12;
        reset = 0;

        // Avanza el PC automáticamente y muestra instrucción y campos
        for (i = 0; i < 12; i = i + 1) begin
            @(posedge clk);
            next_pc = current_pc + 1; 

            $display("PC=%0d, Instr=%b", current_pc, instruction);
            $display("opcode=%b rs=%b rt=%b rd=%b shamt=%b funct=%b immediate=%b",
                instruction[31:26], // opcode
                instruction[25:21], // rs
                instruction[20:16], // rt
                instruction[15:11], // rd
                instruction[10:6],  // shamt
                instruction[5:0],   // funct
                instruction[15:0]   // immediate
            );
            $display("");
        end

        $finish;
    end

    initial begin
        $dumpfile("pc_imem_tb.vcd");
        $dumpvars(0, testbench_PC_IMEM);
    end

endmodule


//**********************************************************************************************

imem_tb.vcd
$date
	Mon Oct 13 16:42:28 2025
$end
$version
	Icarus Verilog
$end
$timescale
	1s
$end
$scope module testbench_imem $end
$var wire 32 ! instruction [31:0] $end
$var reg 32 " addr [31:0] $end
$var integer 32 # i [31:0] $end
$scope module dut $end
$var wire 32 $ addr [31:0] $end
$var wire 32 % instruction [31:0] $end
$upscope $end
$upscope $end
$enddefinitions $end
$comment Show the parameter values. $end
$dumpall
$end
#0
$dumpvars
b1000100001100000100000 %
b0 $
b0 #
b0 "
b1000100001100000100000 !
$end
#1
b100001000010010000000000001010 !
b100001000010010000000000001010 %
b1 "
b1 $
b1 #
#2
b1000100001100000100000 !
b1000100001100000100000 %
b10 "
b10 $
b10 #
#3
b11001000010100000100010 !
b11001000010100000100010 %
b11 "
b11 $
b11 #
#4
b101001100011100000100100 !
b101001100011100000100100 %
b100 "
b100 $
b100 #
#5
b111010000100100000100101 !
b111010000100100000100101 %
b101 "
b101 $
b101 #
#6
b1001010100101100000101010 !
b1001010100101100000101010 %
b110 "
b110 $
b110 #
#7
b1011011000110100000000000 !
b1011011000110100000000000 %
b111 "
b111 $
b111 #
#8
b1101011100111100000000010 !
b1101011100111100000000010 %
b1000 "
b1000 $
b1000 #
#9
b1111100001000100000100000 !
b1111100001000100000100000 %
b1001 "
b1001 $
b1001 #
#10
b10001100101001100000100010 !
b10001100101001100000100010 %
b1010 "
b1010 $
b1010 #
#11
b10011101001010100000100100 !
b10011101001010100000100100 %
b1011 "
b1011 $
b1011 #
#12
b1100 #
